CHANGELOG.rst
LICENSE
MANIFEST.in
README.rst
pyproject.toml
setup.py
susi/SOMClassifier.py
susi/SOMClustering.py
susi/SOMEstimator.py
susi/SOMPlots.py
susi/SOMRegressor.py
susi/SOMUtils.py
susi/__init__.py
susi.egg-info/PKG-INFO
susi.egg-info/SOURCES.txt
susi.egg-info/dependency_links.txt
susi.egg-info/requires.txt
susi.egg-info/top_level.txt
tests/test_MultiOutput.py
tests/test_SOMClassifier.py
tests/test_SOMClustering.py
tests/test_SOMEstimator.py
tests/test_SOMRegressor.py