Metadata-Version: 2.1
Name: susi
Version: 1.4.3
Summary: Python package for unsupervised, supervised and semi-supervised self-organizing maps (SOM)
Home-page: https://github.com/felixriese/susi
Author: Felix M. Riese
Author-email: github@felixriese.de
License: BSD-3-Clause
Project-URL: Documentation, https://susi.readthedocs.io/en/latest/?badge=latest
Project-URL: Source, https://github.com/felixriese/susi
Project-URL: Tracker, https://github.com/felixriese/susi/issues
Classifier: Programming Language :: Python :: 3
Classifier: Programming Language :: Python :: 3.9
Classifier: Programming Language :: Python :: 3.10
Classifier: Programming Language :: Python :: 3.11
Classifier: Programming Language :: Python :: 3.12
Classifier: Environment :: Console
Classifier: Intended Audience :: Developers
Classifier: Intended Audience :: Education
Classifier: Intended Audience :: Information Technology
Classifier: Intended Audience :: Science/Research
Classifier: License :: OSI Approved :: BSD License
Classifier: Natural Language :: English
Classifier: Operating System :: OS Independent
Classifier: Topic :: Scientific/Engineering
Requires-Python: >=3.9
License-File: LICENSE
Requires-Dist: joblib>=0.13.0
Requires-Dist: numpy>=1.18.5
Requires-Dist: scikit-learn>=0.21.1
Requires-Dist: scipy>=1.3.1
Requires-Dist: tqdm>=4.45.0
Requires-Dist: matplotlib>=3.9.0
Provides-Extra: docs
Requires-Dist: numpydoc; extra == "docs"
Requires-Dist: sphinx; extra == "docs"
Requires-Dist: sphinx-autobuild; extra == "docs"
Requires-Dist: sphinx_rtd_theme; extra == "docs"
Provides-Extra: examples
Requires-Dist: notebook>=6.0.0; extra == "examples"
Requires-Dist: seaborn>=0.11.0; extra == "examples"
Requires-Dist: pandas>=1.1.5; extra == "examples"
Provides-Extra: tests
Requires-Dist: pytest; extra == "tests"
Requires-Dist: pytest-cov; extra == "tests"
Requires-Dist: codecov; extra == "tests"
Requires-Dist: nbval; extra == "tests"
Requires-Dist: coverage; extra == "tests"
Provides-Extra: formatting
Requires-Dist: black; extra == "formatting"
Requires-Dist: isort; extra == "formatting"
